apoclypsebm/__init__.py
apoclypsebm/apoclypse-0.cl
apoclypsebm/apoclypse-loopy.cl
apoclypsebm/bitcoin.py
apoclypsebm/command.py
apoclypsebm/detect.py
apoclypsebm/ioutil.py
apoclypsebm/log.py
apoclypsebm/sha256.py
apoclypsebm/switch.py
apoclypsebm/util.py
apoclypsebm/version.py
apoclypsebm/mining/__init__.py
apoclypsebm/mining/base.py
apoclypsebm/mining/bfl.py
apoclypsebm/mining/opencl.py
apoclypsebm/work_sources/__init__.py
apoclypsebm/work_sources/base.py
apoclypsebm/work_sources/getblocktemplate.py
apoclypsebm/work_sources/getwork.py
apoclypsebm/work_sources/stratum.py
apoclypsebm-1.1.4.dist-info/LICENSE
apoclypsebm-1.1.4.dist-info/METADATA
apoclypsebm-1.1.4.dist-info/WHEEL
apoclypsebm-1.1.4.dist-info/entry_points.txt
apoclypsebm-1.1.4.dist-info/top_level.txt
apoclypsebm-1.1.4.dist-info/RECORD
