Metadata-Version: 2.1
Name: apoclypsebm
Version: 1.1.4
Summary: The ApoCLypse Bitcoin Miner
Home-page: https://github.com/JustinTArthur/apoclypsebm/
Author: Justin T. Arthur
Author-email: justinarthur@gmail.com
License: UNKNOWN
Platform: UNKNOWN
Classifier: License :: Public Domain
Requires-Python: >=3.6
Requires-Dist: pyopencl (<=2020.1,>=2017.2)
Requires-Dist: pyserial (>=2.6)
Requires-Dist: PySocks (>=1.6.0)
